[
  {
    "id": "shower-caddy-simplehuman-tension",
    "imageUrl": "",
    "priceMin": 79,
    "priceMax": 119,
    "category": "home",
    "badge": "🏠",
    "name": {
      "en": "simplehuman Tension Shower Caddy",
      "ja": "シンプルヒューマン テンションシャワーキャディ"
    },
    "description": {
      "en": "simplehuman 3-shelf tension pole shower caddy, anodized aluminum and stainless steel, adjustable height 218–274 cm, 3.5 kg capacity per shelf, built-in razor holder and soap dish.",
      "ja": "シンプルヒューマン3段テンションポールシャワーキャディ、アノダイズドアルミ+ステンレス鋼製、高さ調節218〜274cm、1棚あたり3.5kg耐荷重、内蔵カミソリホルダー・ソープディッシュ付。"
    },
    "links": [
      {
        "network": "direct",
        "productId": "https://www.simplehuman.com/collections/shower-caddies",
        "markets": ["global"],
        "approved": false
      }
    ]
  },
  {
    "id": "shower-caddy-umbra-flex",
    "imageUrl": "",
    "priceMin": 39,
    "priceMax": 65,
    "category": "home",
    "badge": "🏠",
    "name": {
      "en": "Umbra Flex Shower Caddy",
      "ja": "アンブラ フレックス シャワーキャディ"
    },
    "description": {
      "en": "Umbra Flex 5-shelf hanging shower caddy, flexible silicone straps fit showerheads up to 4 cm diameter, stainless steel frame, 27×14×75 cm, drainage holes on every shelf.",
      "ja": "アンブラ フレックス5段ハンギングシャワーキャディ、直径4cmまでのシャワーヘッドに対応するシリコンストラップ、ステンレス鋼製フレーム、27×14×75cm、全棚に排水穴あり。"
    },
    "links": [
      {
        "network": "direct",
        "productId": "https://www.umbra.com/collections/shower-caddies",
        "markets": ["global"],
        "approved": false
      }
    ]
  },
  {
    "id": "shower-caddy-yamazaki-tower-jp",
    "imageUrl": "",
    "priceMin": 2860,
    "priceMax": 5280,
    "category": "home",
    "badge": "🏠",
    "name": {
      "en": "Yamazaki Tower Shower Caddy (Japan)",
      "ja": "山崎実業 タワー シャワーキャディ"
    },
    "description": {
      "en": "Yamazaki Tower magnetic-mount shower caddy for Japanese steel-panel bathrooms, rust-resistant powder coat, 23×8×35 cm, 1.5 kg capacity, no screws or adhesive required on magnetic walls.",
      "ja": "日本の鋼製パネルバスルーム向け山崎実業タワー マグネット取付シャワーキャディ、錆びにくいパウダーコート、23×8×35cm、1.5kg耐荷重、マグネット壁はネジ・接着剤不要。"
    },
    "links": [
      {
        "network": "direct",
        "productId": "https://www.amazon.co.jp/s?k=山崎実業+タワー+シャワーキャディ+マグネット",
        "markets": ["global"],
        "approved": false
      }
    ]
  },
  {
    "id": "shower-caddy-zenna-home-expandable",
    "imageUrl": "",
    "priceMin": 25,
    "priceMax": 45,
    "category": "home",
    "badge": "🏠",
    "name": {
      "en": "Zenna Home Expandable Tension Shower Caddy",
      "ja": "ゼナホーム 伸縮テンション シャワーキャディ"
    },
    "description": {
      "en": "Zenna Home 4-tier expandable tension pole shower caddy, chrome-plated steel, adjustable height 183–274 cm, expandable shelf width 28–38 cm, includes soap dish and razor holder.",
      "ja": "ゼナホーム4段伸縮テンションポールシャワーキャディ、クロムメッキ鋼製、高さ調節183〜274cm、棚幅28〜38cm伸縮可能、ソープディッシュ・カミソリホルダー付。"
    },
    "links": [
      {
        "network": "direct",
        "productId": "https://www.amazon.com/s?k=zenna+home+expandable+tension+shower+caddy",
        "markets": ["global"],
        "approved": false
      }
    ]
  },
  {
    "id": "shower-caddy-interdesign-forma",
    "imageUrl": "",
    "priceMin": 18,
    "priceMax": 35,
    "category": "home",
    "badge": "🏠",
    "name": {
      "en": "InterDesign Forma Suction Shower Caddy",
      "ja": "インターデザイン フォルマ 吸盤シャワーキャディ"
    },
    "description": {
      "en": "InterDesign Forma 2-shelf suction shower caddy, chrome-finish steel wire, 24×12×32 cm, 4 heavy-duty suction cups rated to 2 kg per caddy, removable for cleaning.",
      "ja": "インターデザイン フォルマ2段吸盤シャワーキャディ、クローム仕上げスチールワイヤー、24×12×32cm、キャディ全体で2kg対応の強力吸盤×4個、洗浄時取外し可能。"
    },
    "links": [
      {
        "network": "direct",
        "productId": "https://www.amazon.com/s?k=interdesign+forma+suction+shower+caddy",
        "markets": ["global"],
        "approved": false
      }
    ]
  }
]
